{
    "packages": {
        "all": [
            "adobe-source-code-pro-fonts",
            "adobe-source-sans-pro-fonts",
            "alacritty",
            "albert",
            "appimagelauncher",
            "clang",
            "cmake",
            "code",
            "cowsay",
            "curl",
            "dash",
            "discord",
            "docker",
            "docker-compose",
            "exa",
            "fcron",
            "firefox-developer-edition",
            "flac",
            "flameshot",
            "fzf",
            "gcc",
            "gdm3setup",
            "git",
            "gitkraken",
            "gnome-shell-extensions",
            "google-chrome",
            "google-cloud-sdk",
            "gparted",
            "htop",
            "indicator-kdeconnect",
            "jdk-openjdk",
            "jetbrains-toolbox",
            "jq",
            "languagetool",
            "lsof",
            "mediainfo",
            "megasync-git",
            "mktorrent",
            "mpv",
            "neofetch",
            "neovim",
            "nodejs",
            "npm",
            "noto-fonts",
            "pacman-contrib",
            "pixbuf-webp-thumbnailer",
            "ranger",
            "rclone",
            "sxhkd",
            "yadm-git",
            "zsh"
        ],
        "desktop": [],
        "laptop": [],
        "on-hold": [
            "i3",
            "polybar",
            "gitflow-avh"
        ]
    }
}
